plot_field/VLASS_dyn_summary.php
plot_field/__init__.py
plot_field/fit_synchrotron_spectrum.py
plot_field/plot_field.py
plot_field/vlass_search.py
lofar_vlbi_plot-2026.1.1.dist-info/METADATA
lofar_vlbi_plot-2026.1.1.dist-info/WHEEL
lofar_vlbi_plot-2026.1.1.dist-info/entry_points.txt
lofar_vlbi_plot-2026.1.1.dist-info/top_level.txt
lofar_vlbi_plot-2026.1.1.dist-info/RECORD
