Metadata-Version: 2.4
Name: lofar-vlbi-plot
Version: 2026.1.1
Summary: Repository containing the cli tool for LOFAR-VLBI plot_field
Author: James Petley, Frits Sweijen, Leah Morabito
License-Expression: GPL-3.0-or-later
Project-URL: Repository, https://github.com/LOFAR-VLBI/plot_field
Keywords: radio,astronomy,VLBI,LOFAR
Requires-Python: >=3.11
Requires-Dist: astropy>=7.0.0
Requires-Dist: astroquery>=0.4.11
Requires-Dist: matplotlib>=3.9.3
Requires-Dist: numpy>=2.3.5
Requires-Dist: pyvo>=1.6
Requires-Dist: requests>=2.32.3
Requires-Dist: scipy>=1.14.1
Requires-Dist: setuptools>=80.9.0
